grouper_python/__init__.py
grouper_python/attribute.py
grouper_python/group.py
grouper_python/membership.py
grouper_python/privilege.py
grouper_python/py.typed
grouper_python/stem.py
grouper_python/subject.py
grouper_python/template.py
grouper_python/util.py
grouper_python/objects/__init__.py
grouper_python/objects/attribute.py
grouper_python/objects/base.py
grouper_python/objects/client.py
grouper_python/objects/exceptions.py
grouper_python/objects/group.py
grouper_python/objects/membership.py
grouper_python/objects/person.py
grouper_python/objects/privilege.py
grouper_python/objects/stem.py
grouper_python/objects/subject.py
grouper_python-0.1.4.dist-info/licenses/LICENSE
grouper_python-0.1.4.dist-info/METADATA
grouper_python-0.1.4.dist-info/WHEEL
grouper_python-0.1.4.dist-info/top_level.txt
grouper_python-0.1.4.dist-info/RECORD
